restcall/__init__.py
restcall/__main__.py
restcall/curlify.py
restcall/restcall.py
restcall-1.3.0.dist-info/licenses/LICENSE
restcall-1.3.0.dist-info/METADATA
restcall-1.3.0.dist-info/WHEEL
restcall-1.3.0.dist-info/entry_points.txt
restcall-1.3.0.dist-info/top_level.txt
restcall-1.3.0.dist-info/RECORD
