Metadata-Version: 2.4
Name: restcall
Version: 1.3.0
Summary: A small JSON-based command-line utility to make REST calls
Author-email: Subhadip Ghosh <subhadip.sky@gmail.com>
License: MIT License
Project-URL: Homepage, https://github.com/subhadig/restcall
Project-URL: Changelog, https://github.com/subhadig/restcall/blob/master/CHANGELOG.md
Keywords: rest,client,cli
Classifier: License :: OSI Approved :: MIT License
Classifier: Programming Language :: Python
Classifier: Programming Language :: Python :: 3
Requires-Python: >=3.9
License-File: LICENSE
Requires-Dist: requests
Requires-Dist: urllib3
Requires-Dist: uncurl
Dynamic: license-file
